{"AB99":["GB","AB99","Aberdeen City","Scotland","SCT","","","Aberdeen City","S12000033","57.1113","-2.094","1"],"AB23":["GB","AB23","Mundurno","Scotland","SCT","Aberdeen City","","","","57.2327","-2.0786","3"],"AB30":["GB","AB30","Pert","Scotland","SCT","Angus","ANS","","","56.8466","-2.4779","4"],"AB31":["GB","AB31","Blackness","Scotland","SCT","Aberdeenshire","ABD","","","57.0961","-2.5445","3"],"AB32":["GB","AB32","Blackchambers","Scotland","SCT","Aberdeenshire","ABD","","","57.1528","-2.3624","3"],"AB33":["GB","AB33","Kingsford","Scotland","SCT","Aberdeenshire","ABD","","","57.2254","-2.7427","3"],"AB34":["GB","AB34","Birsemore","Scotland","SCT","Aberdeenshire","ABD","","","57.0893","-2.8258","3"],"AB35":["GB","AB35","Linn of Muick Cottage","Scotland","SCT","Aberdeenshire","ABD","","","57.0387","-3.1473","3"],"AB36":["GB","AB36","Boultenstone","Scotland","SCT","Aberdeenshire","ABD","","","57.197","-3.0687","3"],"AB41":["GB","AB41","Leask","Scotland","SCT","Aberdeenshire","ABD","","","57.3571","-2.2412","3"],"AB42":["GB","AB42","Blackhill","Scotland","SCT","Aberdeenshire","ABD","","","57.4785","-1.9286","3"],"AB43":["GB","AB43","Towie","Scotland","SCT","Aberdeenshire","ABD","","","57.657","-2.0448","4"],"AB44":["GB","AB44","Newtown","Scotland","SCT","Aberdeenshire","ABD","","","57.6683","-2.4924","4"],"AB45":["GB","AB45","Ardiecow","Scotland","SCT","Moray","MRY","","","57.5683","-2.5106","3"],"AB51":["GB","AB51","Lyne","Scotland","SCT","Aberdeenshire","ABD","","","57.288","-2.404","4"],"AB52":["GB","AB52","Ardlair","Scotland","SCT","Aberdeenshire","ABD","","","57.3403","-2.5935","3"],"AB53":["GB","AB53","Mill of Colp","Scotland","SCT","Aberdeenshire","ABD","","","57.525","-2.3939","3"],"AB54":["GB","AB54","Aldunie","Scotland","SCT","Moray","MRY","","","57.3709","-2.8293","3"],"AB55":["GB","AB55","Farmtown","Scotland","SCT","Moray","MRY","","","57.4458","-3.1777","3"],"AB37":["GB","AB37","Craggan","Scotland","SCT","Moray","MRY","","","57.2616","-3.3456","3"],"AB38":["GB","AB38","Ringorm","Scotland","SCT","Moray","MRY","","","57.4863","-3.2269","3"],"AB56":["GB","AB56","Slackhead","Scotland","SCT","Moray","MRY","","","57.6746","-2.9278","3"],"AB10":["GB","AB10","Aberdeen","Scotland","SCT","Aberdeenshire","","","","57.1437","-2.0981","4"],"AB11":["GB","AB11","Aberdeen","Scotland","SCT","Aberdeenshire","","","","57.1437","-2.0981","4"],"AB12":["GB","AB12","Aberdeen","Scotland","SCT","Aberdeenshire","","","","57.1437","-2.0981","4"],"AB13":["GB","AB13","Aberdeen","Scotland","SCT","Aberdeenshire","","","","57.1086","-2.2392","4"],"AB14":["GB","AB14","Peterculter","Scotland","SCT","","","","","57.0993","-2.2659","4"],"AB15":["GB","AB15","Aberdeen","Scotland","SCT","Aberdeenshire","","","","57.1378","-2.1663","4"],"AB16":["GB","AB16","Aberdeen","Scotland","SCT","Aberdeenshire","","","","57.16","-2.1567","4"],"AB21":["GB","AB21","Aberdeen","Scotland","SCT","Aberdeenshire","","","","57.2111","-2.2037","4"],"AB22":["GB","AB22","Danestone","Scotland","SCT","Aberdeen City","","","","57.1865","-2.1214","1"],"AB24":["GB","AB24","Aberdeen","Scotland","SCT","Aberdeenshire","","","","57.1437","-2.0981","4"],"AB25":["GB","AB25","Aberdeen","Scotland","SCT","Aberdeenshire","","","","57.1437","-2.0981","4"],"AB39":["GB","AB39","Aberdeen","Scotland","SCT","Aberdeenshire","","","","56.9773","-2.2184","4"]}