{"CO10":["GB","CO10","Foxearth","England","ENG","Essex","11609034","","","52.0691","0.6759","3"],"CO11":["GB","CO11","Cattawade","England","ENG","Essex","11609034","","","51.9291","1.0935","3"],"CO6":["GB","CO6","Broad Green","England","ENG","Essex","11609034","","","51.939","0.8209","3"],"CO7":["GB","CO7","Aingers Green","England","ENG","Essex","11609034","","","51.8828","1.0046","3"],"CO8":["GB","CO8","Alphamstone","England","ENG","Essex","11609034","","","51.9827","0.7325","3"],"CO1":["GB","CO1","Colchester","England","ENG","Essex","11609034","","","51.8892","0.9042","4"],"CO12":["GB","CO12","Great Oakley","England","ENG","Essex","11609034","","","51.9031","1.1881","4"],"CO13":["GB","CO13","Kirby le Soken","England","ENG","Essex","11609034","","","51.8362","1.2249","3"],"CO14":["GB","CO14","Walton-on-Naze","England","ENG","Essex","11609034","","","51.8482","1.2674","4"],"CO15":["GB","CO15","Great Clacton","England","ENG","Essex","11609034","","","51.8046","1.1547","4"],"CO16":["GB","CO16","Beaumont","England","ENG","Essex","11609034","","","51.8211","1.1226","3"],"CO2":["GB","CO2","Blackheath","England","ENG","Essex","11609034","","","51.8694","0.8941","4"],"CO3":["GB","CO3","Beacon End","England","ENG","Essex","11609034","","","51.8847","0.859","3"],"CO4":["GB","CO4","Langham","England","ENG","Essex","11609034","","","51.9488","0.9433","4"],"CO5":["GB","CO5","Smythe's Green","England","ENG","Essex","11609034","","","51.8271","0.8248","3"],"CO9":["GB","CO9","Whiteash Green","England","ENG","Essex","11609034","","","51.995","0.5844","3"]}