{"SY1":["GB","SY1","Battlefield","England","ENG","Shropshire","11609013","","","52.7234","-2.7415","4"],"SY10":["GB","SY10","Llansilin","Wales","WLS","Powys","POW","","","52.8457","-3.1758","4"],"SY11":["GB","SY11","Rhyn","England","ENG","Shropshire","11609013","","","52.8054","-2.9458","3"],"SY12":["GB","SY12","Dudleston Heath","England","ENG","Shropshire","11609013","","","52.8888","-2.8656","3"],"SY13":["GB","SY13","Hanmer","Wales","WLS","Wrexham","WRX","","","52.9511","-2.8129","4"],"SY15":["GB","SY15","Abermule","Wales","WLS","Powys","POW","","","52.5434","-3.2372","4"],"SY2":["GB","SY2","Sutton","England","ENG","Shropshire","11609013","","","52.7065","-2.7295","4"],"SY21":["GB","SY21","Llanfair Caereinion","Wales","WLS","Powys","POW","","","52.6479","-3.3267","4"],"SY3":["GB","SY3","The Isle","England","ENG","Shropshire","11609013","","","52.699","-2.7725","3"],"SY4":["GB","SY4","Ensdon","England","ENG","Shropshire","11609013","","","52.691","-2.6049","3"],"SY5":["GB","SY5","Criggion","Wales","WLS","Powys","POW","","","52.7297","-3.0456","4"],"SY6":["GB","SY6","Minton","England","ENG","Shropshire","11609013","","","52.5364","-2.7923","3"],"SY7":["GB","SY7","Brampton Bryan","England","ENG","Herefordshire","11609017","","","52.3415","-2.9292","3"],"SY8":["GB","SY8","Little Hereford","England","ENG","Herefordshire","11609017","","","52.3148","-2.6555","3"],"SY9":["GB","SY9","Colebatch","Wales","WLS","Shropshire","SHR","","","52.4843","-3.0209","3"],"SY99":["GB","SY99","Shrewsbury","England","ENG","Shropshire","11609013","","","52.7101","-2.7521","4"],"SY14":["GB","SY14","Bickerton","England","ENG","Cheshire","2653234","","","53.0786","-2.7264","3"],"SY22":["GB","SY22","Four Crosses","Wales","WLS","Powys","POW","","","52.75","-3.0833","4"],"SY20":["GB","SY20","Abercegir","Wales","WLS","Powys","POW","","","52.5575","-3.8393","3"],"SY23":["GB","SY23","Capel Dewi","Wales","WLS","Ceredigion","CGN","","","52.3803","-4.0506","4"],"SY24":["GB","SY24","Bont-goch","Wales","WLS","Ceredigion","CGN","","","52.4733","-4.0285","3"],"SY25":["GB","SY25","Ysbyty Ystwyth","Wales","WLS","Ceredigion","CGN","","","52.2528","-3.9294","3"],"SY16":["GB","SY16","New Mills","Wales","WLS","Powys","POW","","","52.5207","-3.3125","4"],"SY17":["GB","SY17","Llawryglyn","Wales","WLS","Powys","POW","","","52.5197","-3.4729","3"],"SY18":["GB","SY18","Pant Mawr","Wales","WLS","Powys","POW","","","52.428","-3.573","3"],"SY19":["GB","SY19","Bont Dolgadfan","Wales","WLS","Powys","POW","","","52.5792","-3.6344","3"]}